RSIDBuildTranslator/__init__.py
RSIDBuildTranslator/cli.py
RSIDBuildTranslator/main.py
RSIDBuildTranslator/pytest.ini
RSIDBuildTranslator/utils.py
RSIDBuildTranslator/modes/__init__.py
RSIDBuildTranslator/modes/mode_chrpos37.py
RSIDBuildTranslator/modes/mode_chrpos38.py
RSIDBuildTranslator/modes/mode_rsid.py
rsidbuildtranslator-1.0.7.dist-info/METADATA
rsidbuildtranslator-1.0.7.dist-info/WHEEL
rsidbuildtranslator-1.0.7.dist-info/entry_points.txt
rsidbuildtranslator-1.0.7.dist-info/licenses/LICENSE
rsidbuildtranslator-1.0.7.dist-info/RECORD
